DSGTAthleticsScrapers/HoopMathScraper.py
DSGTAthleticsScrapers/NCAAScrapers.py
DSGTAthleticsScrapers/__init__.py
DSGTAthleticsScrapers-0.0.2.dist-info/LICENSE
DSGTAthleticsScrapers-0.0.2.dist-info/METADATA
DSGTAthleticsScrapers-0.0.2.dist-info/WHEEL
DSGTAthleticsScrapers-0.0.2.dist-info/top_level.txt
DSGTAthleticsScrapers-0.0.2.dist-info/RECORD
